{
  "project_info": {
    "project_number": "17483521318",
    "project_id": "trudyagi-8264e",
    "storage_bucket": "trudyagi-8264e.appspot.com"
  },
  "client": [
    {
      "client_info": {
        "mobilesdk_app_id": "1:17483521318:android:0247d3d3730427a2bbf5e7",
        "android_client_info": {
          "package_name": "com.example.testapp"
        }
      },
      "oauth_client": [
        {
          "client_id": "17483521318-vi6auqbdt4moa7vqiiuplcmtjopo1klp.apps.googleusercontent.com",
          "client_type": 3
        }
      ],
      "api_key": [
        {
          "current_key": "AIzaSyDMkjBZA5mgSfuCYK-R9i37X_1BvHpJ_cg"
        }
      ],
      "services": {
        "appinvite_service": {
          "other_platform_oauth_client": [
            {
              "client_id": "17483521318-vi6auqbdt4moa7vqiiuplcmtjopo1klp.apps.googleusercontent.com",
              "client_type": 3
            }
          ]
        }
      }
    }
  ],
  "configuration_version": "1"
}